puckepy-1.0.1.dist-info/METADATA
puckepy-1.0.1.dist-info/WHEEL
puckepy-1.0.1.dist-info/license_files/LICENSE
puckepy/formalism/__init__.pyi
puckepy/formalism/__init__.py
puckepy/formalism/formalism.pyi
puckepy/formalism/formalism.py
puckepy/confsampling/confsampling.py
puckepy/confsampling/__init__.pyi
puckepy/confsampling/__init__.py
puckepy/confsampling/confsampling.pyi
puckepy/geometry/__init__.pyi
puckepy/geometry/__init__.py
puckepy/geometry/geometry.py
puckepy/geometry/geometry.pyi
puckepy/__init__.pyi
puckepy/__init__.py
puckepy/puckepy.abi3.so
puckepy-1.0.1.dist-info/RECORD
