Metadata-Version: 2.3
Name: puckepy
Version: 1.0.1
License-File: LICENSE
Summary: Quantify conformations of molecules
Home-Page: https://github.com/jrihon/puckepy
Author: Jérôme Rihon <jeromerihon@gmail.com>
Author-email: Jérôme Rihon <jeromerihon@gmail.com>
License: MIT
Requires-Python: >=3.12
Project-URL: Source Code, https://github.com/jrihon/puckepy
